laerke_eu_pressure_reading_plugin/__init__.py
laerke_eu_pressure_reading_plugin/additional_config.ini
laerke_eu_pressure_reading_plugin/additional_sql.sql
laerke_eu_pressure_reading_plugin/exportable_datasets/laerke_eu_pressure_readings.yaml
laerke_eu_pressure_reading_plugin/ui/contrib/charts/pressure.yaml
laerke_eu_pressure_reading_plugin/ui/contrib/jobs/laerke_eu_pressure_reading.yaml
laerke_eu_pressure_reading_plugin-0.9.0.dist-info/LICENSE.txt
laerke_eu_pressure_reading_plugin-0.9.0.dist-info/METADATA
laerke_eu_pressure_reading_plugin-0.9.0.dist-info/WHEEL
laerke_eu_pressure_reading_plugin-0.9.0.dist-info/entry_points.txt
laerke_eu_pressure_reading_plugin-0.9.0.dist-info/top_level.txt
laerke_eu_pressure_reading_plugin-0.9.0.dist-info/RECORD
