Metadata-Version: 2.2
Name: laerke-eu-pressure-reading-plugin
Version: 0.9.0
Summary: Pioreactor plugin that returns pressure readings every interval from an laerke.eu pressure sensor.
Home-page: https://laerke.eu/
Author: Martin Malthe Borch and Lars Woetmann Pedersen
Author-email: mmbo@biosustain.dtu.dk
License: MIT
License-File: LICENSE.txt
Requires-Dist: smbus2
Dynamic: author
Dynamic: author-email
Dynamic: description
Dynamic: description-content-type
Dynamic: home-page
Dynamic: license
Dynamic: requires-dist
Dynamic: summary
